traffic_data_fetcher-1.1.0.dist-info/licenses/LICENSE
trafficdatafetcher/__init__.py
trafficdatafetcher/__main__.py
trafficdatafetcher/apiclient.py
trafficdatafetcher/csvutils.py
trafficdatafetcher/fetcher.py
trafficdatafetcher/types.py
trafficdatafetcher/commands/__init__.py
trafficdatafetcher/commands/fetchcounts.py
trafficdatafetcher/commands/listdomains.py
trafficdatafetcher/commands/listsites.py
traffic_data_fetcher-1.1.0.dist-info/METADATA
traffic_data_fetcher-1.1.0.dist-info/WHEEL
traffic_data_fetcher-1.1.0.dist-info/entry_points.txt
traffic_data_fetcher-1.1.0.dist-info/top_level.txt
traffic_data_fetcher-1.1.0.dist-info/RECORD
