Metadata-Version: 2.4
Name: traffic-data-fetcher
Version: 1.1.0
Summary: A command line tool for retrieving data from Eco Counter's traffic counter API
Author-email: Christoph Böhme <christoph@b3e.net>
Project-URL: Homepage, https://github.com/cboehme/traffic-data-fetcher
Project-URL: Repository, https://github.com/cboehme/traffic-data-fetcher.git
Project-URL: Issues, https://github.com/cboehme/traffic-data-fetcher/issues
Keywords: eco-counter,bikes,pedestrian,data-collection,traffic-data,traffic-monitoring
Classifier: Development Status :: 5 - Production/Stable
Classifier: License :: OSI Approved :: GNU General Public License v3 or later (GPLv3+)
Classifier: Operating System :: OS Independent
Classifier: Environment :: Console
Classifier: Topic :: Scientific/Engineering :: GIS
Requires-Python: >=3.8
License-File: LICENSE
Requires-Dist: requests==2.32.3
Dynamic: license-file
